[
  {
    "id": 1,
    "type": "collect_y",
    "description": "Collect 5 yellow coins",
    "targetYellowCoins": 5,
    "enemyCount": 7,
    "enemySpeed": 2
  },
  {
    "id": 2,
    "type": "collect_b",
    "description": "collect 10 silver coins",
    "targetBlueCoins": 10,
    "enemyCount": 5,
    "enemySpeed": 2
  },
  {
    "id": 3,
    "type": "feed",
    "description": "Feed 3 rabbits",
    "targetFeed": 3,
    "enemyCount": 5,
    "enemySpeed": 2
  },
  {
    "id": 4,
    "description": "Last for 15 seconds",
    "type": "timer",
    "duration": 15,
    "enemyCount": 10,
    "enemySpeed": 2
  }

]
